pyquibbler_labextension/__init__.py
pyquibbler_labextension/_version.py
pyquibbler_labextension/labextension/package.json
pyquibbler_labextension/labextension/schemas/pyquibbler-labextension/package.json.orig
pyquibbler_labextension/labextension/schemas/pyquibbler-labextension/settings.json
pyquibbler_labextension/labextension/static/455.e2863de3fd60e910c384.js
pyquibbler_labextension/labextension/static/657.e616ab4ac5bd5f7c7aea.js
pyquibbler_labextension/labextension/static/667.8361cf3d48872d85d4d4.js
pyquibbler_labextension/labextension/static/669.4e3b937f5c6cc71ec929.js
pyquibbler_labextension/labextension/static/747.3dacfda904c63238ceb2.js
pyquibbler_labextension/labextension/static/remoteEntry.5b15ba1f6ff9e22bb58b.js
pyquibbler_labextension/labextension/static/style.js
pyquibbler_labextension/labextension/static/third-party-licenses.json
pyquibbler_labextension-1.0.0.data/data/share/jupyter/labextensions/pyquibbler-labextension/install.json
pyquibbler_labextension-1.0.0.data/data/share/jupyter/labextensions/pyquibbler-labextension/package.json
pyquibbler_labextension-1.0.0.data/data/share/jupyter/labextensions/pyquibbler-labextension/schemas/pyquibbler-labextension/package.json.orig
pyquibbler_labextension-1.0.0.data/data/share/jupyter/labextensions/pyquibbler-labextension/schemas/pyquibbler-labextension/settings.json
pyquibbler_labextension-1.0.0.data/data/share/jupyter/labextensions/pyquibbler-labextension/static/455.e2863de3fd60e910c384.js
pyquibbler_labextension-1.0.0.data/data/share/jupyter/labextensions/pyquibbler-labextension/static/657.e616ab4ac5bd5f7c7aea.js
pyquibbler_labextension-1.0.0.data/data/share/jupyter/labextensions/pyquibbler-labextension/static/667.8361cf3d48872d85d4d4.js
pyquibbler_labextension-1.0.0.data/data/share/jupyter/labextensions/pyquibbler-labextension/static/669.4e3b937f5c6cc71ec929.js
pyquibbler_labextension-1.0.0.data/data/share/jupyter/labextensions/pyquibbler-labextension/static/747.3dacfda904c63238ceb2.js
pyquibbler_labextension-1.0.0.dist-info/METADATA
pyquibbler_labextension-1.0.0.dist-info/WHEEL
pyquibbler_labextension-1.0.0.dist-info/top_level.txt
pyquibbler_labextension-1.0.0.dist-info/RECORD
